calculate_distance/__init__.py
calculate_distance/myfunctions.py
calculate_distance-0.1.0.dist-info/METADATA
calculate_distance-0.1.0.dist-info/WHEEL
calculate_distance-0.1.0.dist-info/top_level.txt
calculate_distance-0.1.0.dist-info/RECORD
