Metadata-Version: 2.1
Name: calculate_distance
Version: 0.1.0
Summary: my first python library
Author: me
